hop/__init__.py
hop/_client.py
hop/_exceptions.py
hop/_utilities.py
hop/types/groups.py
hop/types/records.py
hop/types/user.py
hop_dev_client-0.1.0.dist-info/METADATA
hop_dev_client-0.1.0.dist-info/WHEEL
hop_dev_client-0.1.0.dist-info/RECORD
