Metadata-Version: 2.3
Name: hop-dev-client
Version: 0.1.0
Summary: Add your description here
Author-email: Parthiban D <parthiban@hop.dev>
Requires-Python: >=3.8
Requires-Dist: authlib>=1.3.1
Requires-Dist: boto3>=1.34.122
Requires-Dist: httpx>=0.27.0
Requires-Dist: pydantic>=2.7.3
Requires-Dist: pytest>=8.2.2
